Metadata-Version: 2.1
Name: mensajes-SMV08
Version: 6.0
Summary: Un paquete para saludar y despedir
Home-page: https://www.sebas.dev
Author: Sebastian Mora
Author-email: hola@sebas.dev
Classifier: Environment :: Console
Classifier: Intended Audience :: Developers
Classifier: License :: OSI Approved :: MIT License
Classifier: Operating System :: OS Independent
Classifier: Programming Language :: Python
Classifier: Programming Language :: Python :: 3.11
Classifier: Topic :: Utilities
License-File: LICENSE
Requires-Dist: numpy ==1.25.2
